cmem_plugin_nextcloud/__init__.py
cmem_plugin_nextcloud/actions.py
cmem_plugin_nextcloud/autocomplete.py
cmem_plugin_nextcloud/download.py
cmem_plugin_nextcloud/list.py
cmem_plugin_nextcloud/nextcloud-download.svg
cmem_plugin_nextcloud/nextcloud-list.svg
cmem_plugin_nextcloud/nextcloud-upload.svg
cmem_plugin_nextcloud/retrieval.py
cmem_plugin_nextcloud/upload.py
cmem_plugin_nextcloud-1.5.0.dist-info/METADATA
cmem_plugin_nextcloud-1.5.0.dist-info/WHEEL
cmem_plugin_nextcloud-1.5.0.dist-info/licenses/LICENSE
cmem_plugin_nextcloud-1.5.0.dist-info/RECORD
